{
    "orders": [
        {
            "orderno": "4545213690",
            "date": "June 30, 2022 1:54:21 PM",
            "trackingno": "52123",
            "customer": {
                "customerid": "785612",
                "fname": "Bhavin",
                "lname": "Babariya",
                "address": "55,amipark society",
                "city": "surat",
                "state": "GJ",
                "zip": "395010"
            }
        },
        {
            "orderno": "4545213691",
            "date": "June 30, 2022 2:04:30 PM",
            "trackingno": "52124",
            "customer": {
                "customerid": "652345",
                "fname": "Jenil",
                "lname": "Bhalala",
                "address": "40,amipark society",
                "city": "surat",
                "state": "GJ",
                "zip": "395010"
            }
        },
        {
            "orderno": "4545213692",
            "date": "June 30, 2022 2:30:20 PM",
            "trackingno": "52124",
            "customer": {
                "customerid": "452312",
                "fname": "Jay",
                "lname": "Savaliya",
                "address": "215,shivnagar society",
                "city": "surat",
                "state": "GJ",
                "zip": "395010"
            }
        },
        {
            "orderno": "4545213693",
            "date": "June 30, 2022 4:15:00 PM",
            "trackingno": "52125",
            "customer": {
                "customerid": "326512",
                "fname": "Hari",
                "lname": "Finaviya",
                "address": "502, Royal Heaven Residency",
                "city": "surat",
                "state": "GJ",
                "zip": "395010"
            }
        }
    ]
}
